chaostp/__init__.py
chaostp/cli.py
chaostp/proxy/__init__.py
chaostp/proxy/actions.py
chaostp/proxy/probes.py
sky_chaostoolkit_toxiproxy_2-0.1.8.dist-info/AUTHORS.rst
sky_chaostoolkit_toxiproxy_2-0.1.8.dist-info/LICENSE
sky_chaostoolkit_toxiproxy_2-0.1.8.dist-info/METADATA
sky_chaostoolkit_toxiproxy_2-0.1.8.dist-info/WHEEL
sky_chaostoolkit_toxiproxy_2-0.1.8.dist-info/top_level.txt
sky_chaostoolkit_toxiproxy_2-0.1.8.dist-info/RECORD
