Metadata-Version: 2.1
Name: sky-chaostoolkit-toxiproxy-2
Version: 0.1.8
Summary: Chaos Toolkit toxiproxy support by SKY
Home-page: http://chaostoolkit.org
Author: Leslie Lintott
Author-email: leslie.lintott@sky.uk
License: Apache License Version 2.0
Platform: UNKNOWN
Classifier: Development Status :: 2 - Pre-Alpha
Classifier: Intended Audience :: Developers
Classifier: License :: Freely Distributable
Classifier: Operating System :: OS Independent
Classifier: License :: OSI Approved :: Apache Software License
Classifier: Programming Language :: Python
Classifier: Programming Language :: Python :: 3
Requires-Python: >=3.5.*
Requires-Dist: toxiproxy-python
Requires-Dist: logzero
Requires-Dist: chaostoolkit-lib
Requires-Dist: pyyaml
Requires-Dist: requests
